AUTHORS.md
CONTRIBUTING.md
LICENSE
MANIFEST.in
README.md
pyproject.toml
setup.cfg
tests/test_enzo.py
tests/test_gamer.py
tests/test_import.py
tests/data/get_test_data.sh
tests/stubs/libyt_v_0_2_stub.py
yt_libyt/__init__.py
yt_libyt/_version.py
yt_libyt/api.py
yt_libyt/data_structures.py
yt_libyt/definitions.py
yt_libyt/fields.py
yt_libyt/io.py
yt_libyt/misc.py
yt_libyt/py.typed
yt_libyt.egg-info/PKG-INFO
yt_libyt.egg-info/SOURCES.txt
yt_libyt.egg-info/dependency_links.txt
yt_libyt.egg-info/not-zip-safe
yt_libyt.egg-info/requires.txt
yt_libyt.egg-info/top_level.txt