Metadata-Version: 2.4
Name: yt_libyt
Version: 0.3.0
Summary: A yt frontend for libyt
Author-email: Shin-Rong Tsai <turquoisea.tsai@gmail.com>, Hsi-Yu Schive <hyschive@gmail.com>, Matthew Turk <matthewturk@gmail.com>
License: 
Project-URL: Homepage, https://github.com/data-exp-lab/yt_libyt
Keywords: yt_libyt
Classifier: Development Status :: 3 - Alpha
Classifier: Intended Audience :: Developers
Classifier: Intended Audience :: Science/Research
Classifier: License :: OSI Approved :: BSD License
Classifier: Natural Language :: English
Classifier: Programming Language :: Python :: 3
Requires-Python: >=3.7
License-File: LICENSE
Requires-Dist: yt
Dynamic: license-file
